pdftowrite/__init__.py
pdftowrite/docs.py
pdftowrite/pdftowrite.py
pdftowrite/utils.py
pdftowrite/writetopdf.py
pdftowrite/data/document.svg
pdftowrite/data/page.svg
pdftowrite-2021.5.3.dist-info/COPYING
pdftowrite-2021.5.3.dist-info/METADATA
pdftowrite-2021.5.3.dist-info/WHEEL
pdftowrite-2021.5.3.dist-info/entry_points.txt
pdftowrite-2021.5.3.dist-info/top_level.txt
pdftowrite-2021.5.3.dist-info/RECORD
