Metadata-Version: 2.1
Name: pdftowrite
Version: 2021.5.3
Summary: PDF <-> Write document converter
Home-page: https://github.com/kosmospredanie/pdftowrite
Author: Космическое П.
Author-email: kosmospredanie@yandex.ru
License: MIT
Project-URL: Source, https://github.com/kosmospredanie/pdftowrite
Project-URL: Bug Tracker, https://github.com/kosmospredanie/pdftowrite/issues
Platform: UNKNOWN
Classifier: Programming Language :: Python :: 3
Classifier: Programming Language :: Python :: 3.7
Classifier: Programming Language :: Python :: 3.8
Classifier: Programming Language :: Python :: 3.9
Classifier: License :: OSI Approved :: MIT License
Requires-Python: >=3.7
Requires-Dist: shortuuid
Requires-Dist: picosvg
